deepimage/__init__.py
deepimage/img_obj.py
deepimage/tests.py
deepimage/tools.py
deepimage-0.0.6.dist-info/METADATA
deepimage-0.0.6.dist-info/RECORD
deepimage-0.0.6.dist-info/WHEEL
deepimage-0.0.6.dist-info/top_level.txt
