Metadata-Version: 2.1
Name: deepimage
Version: 0.0.6
Summary: a lightweight image object library
Home-page: https://github.com/perceptance/deepimage
Author: Jie Feng
Author-email: jiefengdev@gmail.com
License: UNKNOWN
Keywords: computer vision image
Platform: UNKNOWN
Requires-Dist: numpy (==1.14.3)
Requires-Dist: opencv-python (==3.4.0.12)
Requires-Dist: Pillow (==5.1.0)
